vertices_to_h5m/__init__.py
vertices_to_h5m/_version.py
vertices_to_h5m/core.py
vertices_to_h5m-0.1.7.dist-info/LICENSE.txt
vertices_to_h5m-0.1.7.dist-info/METADATA
vertices_to_h5m-0.1.7.dist-info/WHEEL
vertices_to_h5m-0.1.7.dist-info/top_level.txt
vertices_to_h5m-0.1.7.dist-info/RECORD
