Metadata-Version: 2.1
Name: vertices-to-h5m
Version: 0.1.7
Summary: Converts mesh vertices and connectivity to h5m geometry files compatible with DAGMC simulations
Home-page: https://github.com/fusion-energy/vertices_to_h5m
Author: The vertices_to_h5m Development Team
Author-email: mail@jshimwell.com
License: MIT
Project-URL: Source, https://github.com/fusion-energy/vertices_to_h5m
Project-URL: Tracker, https://github.com/fusion-energy/vertices_to_h5m/issues
Classifier: Natural Language :: English
Classifier: Topic :: Scientific/Engineering
Classifier: Programming Language :: Python :: 3
Classifier: Programming Language :: Python :: 3.7
Classifier: Programming Language :: Python :: 3.8
Classifier: Programming Language :: Python :: 3.9
Classifier: Programming Language :: Python :: 3.10
Classifier: License :: OSI Approved :: MIT License
Classifier: Operating System :: OS Independent
Requires-Python: >=3.6
License-File: LICENSE.txt
Requires-Dist: trimesh
Requires-Dist: networkx
Requires-Dist: scipy
Provides-Extra: tests
Requires-Dist: pytest (>=5.4.3) ; extra == 'tests'
Requires-Dist: dagmc-h5m-file-inspector ; extra == 'tests'
Requires-Dist: openmc-data-downloader ; extra == 'tests'
